anyunit/__init__.py
anyunit/converter.py
anyunit/getUnits.py
anyunit/units.py
anyunit-0.1.4.dist-info/licenses/LICENSE
anyunit-0.1.4.dist-info/METADATA
anyunit-0.1.4.dist-info/WHEEL
anyunit-0.1.4.dist-info/top_level.txt
anyunit-0.1.4.dist-info/RECORD
