Metadata-Version: 2.4
Name: anyunit
Version: 0.1.4
Summary: AnyUnit - Universal unit converter
Author-email: argoars <smetankauwu3008@gmail.com>
License: MIT License
Project-URL: Homepage, https://github.com/argoarsiks/AnyUnit
Classifier: Programming Language :: Python :: 3
Classifier: License :: OSI Approved :: MIT License
Requires-Python: >=3.8
License-File: LICENSE
Dynamic: license-file
